{"businesses": [{"id": "JION8hhg7q6zyayHYwhxIw", "alias": "the-high-line-new-york", "name": "The High Line", "image_url": "https://s3-media2.fl.yelpcdn.com/bphoto/8dWtYbMkHKNgyKe5S1DZkA/o.jpg", "is_closed": false, "url": "https://www.yelp.com/biz/the-high-line-new-york?adjust_creative=dMFM0G7PB1QaTw51VlEhfg&utm_campaign=yelp_api_v3&utm_medium=api_v3_business_search&utm_source=dMFM0G7PB1QaTw51VlEhfg", "review_count": 2567, "categories": [{"alias": "parks", "title": "Parks"}], "rating": 4.5, "coordinates": {"latitude": 40.7396039, "longitude": -74.00847657515718}, "transactions": [], "location": {"address1": "820 Washington St", "address2": "", "address3": "", "city": "New York", "zip_code": "10014", "country": "US", "state": "NY", "display_address": ["820 Washington St", "New York, NY 10014"]}, "phone": "+12122069922", "display_phone": "(212) 206-9922", "distance": 4387.905588292356}, {"id": "mjq_dOmCPBBLAnq7PJG9-Q", "alias": "spyscape-new-york", "name": "Spyscape", "image_url": "https://s3-media2.fl.yelpcdn.com/bphoto/RalMMmpRtBX5An6u__Xwyg/o.jpg", "is_closed": false, "url": "https://www.yelp.com/biz/spyscape-new-york?adjust_creative=dMFM0G7PB1QaTw51VlEhfg&utm_campaign=yelp_api_v3&utm_medium=api_v3_business_search&utm_source=dMFM0G7PB1QaTw51VlEhfg", "review_count": 382, "categories": [{"alias": "arts", "title": "Arts & Entertainment"}, {"alias": "venues", "title": "Venues & Event Spaces"}], "rating": 4.5, "coordinates": {"latitude": 40.765436, "longitude": -73.983925}, "transactions": [], "location": {"address1": "928 8th Ave", "address2": null, "address3": "", "city": "New York", "zip_code": "10019", "country": "US", "state": "NY", "display_address": ["928 8th Ave", "New York, NY 10019"]}, "phone": "+12125491941", "display_phone": "(212) 549-1941", "distance": 6512.504360062957}, {"id": "-YPaO4YpJMlagrAwlkhpfA", "alias": "museum-of-sex-new-york", "name": "Museum of Sex", "image_url": "https://s3-media4.fl.yelpcdn.com/bphoto/DKR1jY9FDooNU8M8sTP1Qw/o.jpg", "is_closed": false, "url": "https://www.yelp.com/biz/museum-of-sex-new-york?adjust_creative=dMFM0G7PB1QaTw51VlEhfg&utm_campaign=yelp_api_v3&utm_medium=api_v3_business_search&utm_source=dMFM0G7PB1QaTw51VlEhfg", "review_count": 1441, "categories": [{"alias": "museums", "title": "Museums"}], "rating": 3.0, "coordinates": {"latitude": 40.744086, "longitude": -73.98742}, "transactions": [], "location": {"address1": "233 5th Ave", "address2": "", "address3": "", "city": "New York", "zip_code": "10016", "country": "US", "state": "NY", "display_address": ["233 5th Ave", "New York, NY 10016"]}, "phone": "+12126896337", "display_phone": "(212) 689-6337", "distance": 4184.167853504401}, {"id": "5mOOEmKa5H98m9HT5dam1g", "alias": "oculus-new-york", "name": "Oculus", "image_url": "https://s3-media3.fl.yelpcdn.com/bphoto/qejHTBTfGFzDISqtgc0kRg/o.jpg", "is_closed": false, "url": "https://www.yelp.com/biz/oculus-new-york?adjust_creative=dMFM0G7PB1QaTw51VlEhfg&utm_campaign=yelp_api_v3&utm_medium=api_v3_business_search&utm_source=dMFM0G7PB1QaTw51VlEhfg", "review_count": 357, "categories": [{"alias": "landmarks", "title": "Landmarks & Historical Buildings"}], "rating": 4.5, "coordinates": {"latitude": 40.7115051, "longitude": -74.011386}, "transactions": [], "location": {"address1": "World Trade Center Transportation Hub", "address2": "", "address3": "", "city": "New York", "zip_code": "10006", "country": "US", "state": "NY", "display_address": ["World Trade Center Transportation Hub", "New York, NY 10006"]}, "phone": "", "display_phone": "", "distance": 2760.3123116312845}, {"id": "FCt4zU9tPAewEnEniRRLbg", "alias": "color-factory-new-york", "name": "Color Factory", "image_url": "https://s3-media4.fl.yelpcdn.com/bphoto/9EzdDgTBV2_TlenzxczIVA/o.jpg", "is_closed": false, "url": "https://www.yelp.com/biz/color-factory-new-york?adjust_creative=dMFM0G7PB1QaTw51VlEhfg&utm_campaign=yelp_api_v3&utm_medium=api_v3_business_search&utm_source=dMFM0G7PB1QaTw51VlEhfg", "review_count": 551, "categories": [{"alias": "artmuseums", "title": "Art Museums"}], "rating": 4.0, "coordinates": {"latitude": 40.7257668, "longitude": -74.0053664}, "transactions": [], "location": {"address1": "251 Spring St", "address2": "", "address3": null, "city": "New York", "zip_code": "10013", "country": "US", "state": "NY", "display_address": ["251 Spring St", "New York, NY 10013"]}, "phone": "", "display_phone": "", "distance": 3042.1772529874884}, {"id": "36krOhexcsA8Uetoq52A7g", "alias": "top-of-the-rock-new-york", "name": "Top of the Rock", "image_url": "https://s3-media4.fl.yelpcdn.com/bphoto/REKZQxIKDbyThfGxSzRcCQ/o.jpg", "is_closed": false, "url": "https://www.yelp.com/biz/top-of-the-rock-new-york?adjust_creative=dMFM0G7PB1QaTw51VlEhfg&utm_campaign=yelp_api_v3&utm_medium=api_v3_business_search&utm_source=dMFM0G7PB1QaTw51VlEhfg", "review_count": 1749, "categories": [{"alias": "landmarks", "title": "Landmarks & Historical Buildings"}, {"alias": "observatories", "title": "Observatories"}], "rating": 4.5, "coordinates": {"latitude": 40.7593755, "longitude": -73.9794036288354}, "transactions": [], "location": {"address1": "30 Rockefeller Plz", "address2": "", "address3": "", "city": "New York", "zip_code": "10112", "country": "US", "state": "NY", "display_address": ["30 Rockefeller Plz", "New York, NY 10112"]}, "phone": "+12126982000", "display_phone": "(212) 698-2000", "distance": 5826.390476496187}, {"id": "jF5CrF1BmvhoPlMTp5AoJQ", "alias": "chelsea-market-new-york", "name": "Chelsea Market", "image_url": "https://s3-media3.fl.yelpcdn.com/bphoto/Cc9HPQN5OA9FSUe-aLgBiA/o.jpg", "is_closed": false, "url": "https://www.yelp.com/biz/chelsea-market-new-york?adjust_creative=dMFM0G7PB1QaTw51VlEhfg&utm_campaign=yelp_api_v3&utm_medium=api_v3_business_search&utm_source=dMFM0G7PB1QaTw51VlEhfg", "review_count": 2431, "categories": [{"alias": "publicmarkets", "title": "Public Markets"}], "rating": 4.5, "coordinates": {"latitude": 40.7419711362098, "longitude": -74.0048450364568}, "transactions": [], "price": "$$", "location": {"address1": "75 9th Ave", "address2": "", "address3": null, "city": "New York", "zip_code": "10011", "country": "US", "state": "NY", "display_address": ["75 9th Ave", "New York, NY 10011"]}, "phone": "+12126522111", "display_phone": "(212) 652-2111", "distance": 4451.475271861389}, {"id": "BHlxwBMBIHX0ftiok_OMOQ", "alias": "vessel-new-york-3", "name": "Vessel", "image_url": "https://s3-media2.fl.yelpcdn.com/bphoto/awp4A5JIFJ0Pal-ShVN4gQ/o.jpg", "is_closed": false, "url": "https://www.yelp.com/biz/vessel-new-york-3?adjust_creative=dMFM0G7PB1QaTw51VlEhfg&utm_campaign=yelp_api_v3&utm_medium=api_v3_business_search&utm_source=dMFM0G7PB1QaTw51VlEhfg", "review_count": 494, "categories": [{"alias": "landmarks", "title": "Landmarks & Historical Buildings"}], "rating": 4.5, "coordinates": {"latitude": 40.7538184587518, "longitude": -74.00215228911576}, "transactions": [], "location": {"address1": "20 Hudson Yards", "address2": "", "address3": null, "city": "New York", "zip_code": "10001", "country": "US", "state": "NY", "display_address": ["20 Hudson Yards", "New York, NY 10001"]}, "phone": "+16469543100", "display_phone": "(646) 954-3100", "distance": 5556.307294066028}, {"id": "NvjXqmxfJTBLL7hd7bZAWA", "alias": "seaglass-carousel-new-york", "name": "SeaGlass Carousel", "image_url": "https://s3-media4.fl.yelpcdn.com/bphoto/DIlu8vEf4DfyRrOHieE2GQ/o.jpg", "is_closed": false, "url": "https://www.yelp.com/biz/seaglass-carousel-new-york?adjust_creative=dMFM0G7PB1QaTw51VlEhfg&utm_campaign=yelp_api_v3&utm_medium=api_v3_business_search&utm_source=dMFM0G7PB1QaTw51VlEhfg", "review_count": 202, "categories": [{"alias": "carousels", "title": "Carousels"}], "rating": 4.5, "coordinates": {"latitude": 40.70218869177488, "longitude": -74.01491354138598}, "transactions": [], "location": {"address1": "7 State St", "address2": "", "address3": "The Battery Park", "city": "New York", "zip_code": "10004", "country": "US", "state": "NY", "display_address": ["7 State St", "The Battery Park", "New York, NY 10004"]}, "phone": "+12123443491", "display_phone": "(212) 344-3491", "distance": 3058.2786437188774}, {"id": "0786OmL8aUi9AANE5Jb45Q", "alias": "soho-new-york", "name": "SoHo", "image_url": "https://s3-media1.fl.yelpcdn.com/bphoto/2pIKretSkRJf_NpLLzmDlg/o.jpg", "is_closed": false, "url": "https://www.yelp.com/biz/soho-new-york?adjust_creative=dMFM0G7PB1QaTw51VlEhfg&utm_campaign=yelp_api_v3&utm_medium=api_v3_business_search&utm_source=dMFM0G7PB1QaTw51VlEhfg", "review_count": 83, "categories": [{"alias": "localflavor", "title": "Local Flavor"}], "rating": 4.5, "coordinates": {"latitude": 40.7209000808398, "longitude": -73.9994112137695}, "transactions": [], "location": {"address1": "", "address2": "", "address3": "", "city": "New York", "zip_code": "10012", "country": "US", "state": "NY", "display_address": ["New York, NY 10012"]}, "phone": "", "display_phone": "", "distance": 2302.630734367727}, {"id": "DljEWeF_gztISnZu6_dp6g", "alias": "friends-apartment-new-york", "name": "Friends Apartment", "image_url": "https://s3-media2.fl.yelpcdn.com/bphoto/rq2VoPsjBBRbpaomL7wJUg/o.jpg", "is_closed": false, "url": "https://www.yelp.com/biz/friends-apartment-new-york?adjust_creative=dMFM0G7PB1QaTw51VlEhfg&utm_campaign=yelp_api_v3&utm_medium=api_v3_business_search&utm_source=dMFM0G7PB1QaTw51VlEhfg", "review_count": 26, "categories": [{"alias": "localflavor", "title": "Local Flavor"}], "rating": 4.0, "coordinates": {"latitude": 40.73229, "longitude": -74.00523}, "transactions": [], "location": {"address1": "90 Bedford St", "address2": "", "address3": null, "city": "New York", "zip_code": "10014", "country": "US", "state": "NY", "display_address": ["90 Bedford St", "New York, NY 10014"]}, "phone": "", "display_phone": "", "distance": 3578.8997744005705}, {"id": "VNCaD-j9IrlFVGtg1y4G9g", "alias": "candytopia-new-york-4", "name": "Candytopia", "image_url": "https://s3-media2.fl.yelpcdn.com/bphoto/VXI4dZDmela65ltfNLyVDQ/o.jpg", "is_closed": false, "url": "https://www.yelp.com/biz/candytopia-new-york-4?adjust_creative=dMFM0G7PB1QaTw51VlEhfg&utm_campaign=yelp_api_v3&utm_medium=api_v3_business_search&utm_source=dMFM0G7PB1QaTw51VlEhfg", "review_count": 79, "categories": [{"alias": "museums", "title": "Museums"}], "rating": 4.0, "coordinates": {"latitude": 40.74876742157944, "longitude": -73.9890293294349}, "transactions": [], "location": {"address1": "111 W 32nd St", "address2": "", "address3": null, "city": "New York", "zip_code": "10001", "country": "US", "state": "NY", "display_address": ["111 W 32nd St", "New York, NY 10001"]}, "phone": "", "display_phone": "", "distance": 4720.23155915111}, {"id": "5vVD0YxnyJjg-CXUbNGLQA", "alias": "dumbo-brooklyn", "name": "Dumbo", "image_url": "https://s3-media1.fl.yelpcdn.com/bphoto/ScAm65MW6xqzHovrdvdNXQ/o.jpg", "is_closed": false, "url": "https://www.yelp.com/biz/dumbo-brooklyn?adjust_creative=dMFM0G7PB1QaTw51VlEhfg&utm_campaign=yelp_api_v3&utm_medium=api_v3_business_search&utm_source=dMFM0G7PB1QaTw51VlEhfg", "review_count": 128, "categories": [{"alias": "localflavor", "title": "Local Flavor"}], "rating": 4.5, "coordinates": {"latitude": 40.7032167814868, "longitude": -73.9895866404601}, "transactions": [], "location": {"address1": "", "address2": "", "address3": "", "city": "Brooklyn", "zip_code": "11201", "country": "US", "state": "NY", "display_address": ["Brooklyn, NY 11201"]}, "phone": "", "display_phone": "", "distance": 971.2693067114623}, {"id": "IMA18MENFeqdZc5YVh8njg", "alias": "brooklyn-botanic-garden-brooklyn-2", "name": "Brooklyn Botanic Garden", "image_url": "https://s3-media2.fl.yelpcdn.com/bphoto/gVyOrt9ixKc7CJygr5tJYg/o.jpg", "is_closed": false, "url": "https://www.yelp.com/biz/brooklyn-botanic-garden-brooklyn-2?adjust_creative=dMFM0G7PB1QaTw51VlEhfg&utm_campaign=yelp_api_v3&utm_medium=api_v3_business_search&utm_source=dMFM0G7PB1QaTw51VlEhfg", "review_count": 1028, "categories": [{"alias": "gardens", "title": "Botanical Gardens"}], "rating": 4.5, "coordinates": {"latitude": 40.6692899, "longitude": -73.9633}, "transactions": [], "location": {"address1": "990 Washington Ave", "address2": "", "address3": "", "city": "Brooklyn", "zip_code": "11225", "country": "US", "state": "NY", "display_address": ["990 Washington Ave", "Brooklyn, NY 11225"]}, "phone": "+17186237200", "display_phone": "(718) 623-7200", "distance": 4400.281086225832}, {"id": "MEzvOZ34GFaiEAaVQFvggg", "alias": "harry-potter-new-york-new-york-2", "name": "Harry Potter New York", "image_url": "https://s3-media3.fl.yelpcdn.com/bphoto/iq-rF6K-QYLMjfuipqhk1Q/o.jpg", "is_closed": false, "url": "https://www.yelp.com/biz/harry-potter-new-york-new-york-2?adjust_creative=dMFM0G7PB1QaTw51VlEhfg&utm_campaign=yelp_api_v3&utm_medium=api_v3_business_search&utm_source=dMFM0G7PB1QaTw51VlEhfg", "review_count": 327, "categories": [{"alias": "media", "title": "Books, Mags, Music & Video"}, {"alias": "souvenirs", "title": "Souvenir Shops"}, {"alias": "themedcafes", "title": "Themed Cafes"}], "rating": 4.0, "coordinates": {"latitude": 40.74062579508055, "longitude": -73.98963264866728}, "transactions": [], "location": {"address1": "935 Broadway", "address2": null, "address3": "", "city": "New York", "zip_code": "10010", "country": "US", "state": "NY", "display_address": ["935 Broadway", "New York, NY 10010"]}, "phone": "", "display_phone": "", "distance": 3843.6465456063693}, {"id": "shJoVEcpbABowY6EIkscHw", "alias": "chinatown-new-york-4", "name": "Chinatown", "image_url": "https://s3-media1.fl.yelpcdn.com/bphoto/Vkmp6lFBRKrkz6Zt2Xu4YA/o.jpg", "is_closed": false, "url": "https://www.yelp.com/biz/chinatown-new-york-4?adjust_creative=dMFM0G7PB1QaTw51VlEhfg&utm_campaign=yelp_api_v3&utm_medium=api_v3_business_search&utm_source=dMFM0G7PB1QaTw51VlEhfg", "review_count": 125, "categories": [{"alias": "yelpevents", "title": "Yelp Events"}], "rating": 4.0, "coordinates": {"latitude": 40.71578, "longitude": -73.99774}, "transactions": [], "location": {"address1": "7 Elizabeth St", "address2": "", "address3": "", "city": "New York", "zip_code": "10013", "country": "US", "state": "NY", "display_address": ["7 Elizabeth St", "New York, NY 10013"]}, "phone": "", "display_phone": "", "distance": 1844.3460725636928}, {"id": "u82BF9HaRiFXNvRaDZ2d2g", "alias": "edge-new-york-2", "name": "Edge", "image_url": "https://s3-media3.fl.yelpcdn.com/bphoto/cDTfBNF1YYdlBObhorGjJg/o.jpg", "is_closed": false, "url": "https://www.yelp.com/biz/edge-new-york-2?adjust_creative=dMFM0G7PB1QaTw51VlEhfg&utm_campaign=yelp_api_v3&utm_medium=api_v3_business_search&utm_source=dMFM0G7PB1QaTw51VlEhfg", "review_count": 123, "categories": [{"alias": "observatories", "title": "Observatories"}], "rating": 3.5, "coordinates": {"latitude": 40.75408980795579, "longitude": -74.00093991165897}, "transactions": [], "location": {"address1": "30 Hudson Yards", "address2": "", "address3": null, "city": "New York", "zip_code": "10001", "country": "US", "state": "NY", "display_address": ["30 Hudson Yards", "New York, NY 10001"]}, "phone": "+13322048500", "display_phone": "(332) 204-8500", "distance": 5550.0286655198415}, {"id": "V2moAvUHJARiEXp6YngC3w", "alias": "one-world-observatory-new-york", "name": "One World Observatory", "image_url": "https://s3-media3.fl.yelpcdn.com/bphoto/VRDmdf2LSCdoLwXok4GJqA/o.jpg", "is_closed": false, "url": "https://www.yelp.com/biz/one-world-observatory-new-york?adjust_creative=dMFM0G7PB1QaTw51VlEhfg&utm_campaign=yelp_api_v3&utm_medium=api_v3_business_search&utm_source=dMFM0G7PB1QaTw51VlEhfg", "review_count": 784, "categories": [{"alias": "observatories", "title": "Observatories"}], "rating": 4.0, "coordinates": {"latitude": 40.71305802279098, "longitude": -74.0131694239426}, "transactions": [], "location": {"address1": "117 West St", "address2": "", "address3": "", "city": "New York", "zip_code": "10007", "country": "US", "state": "NY", "display_address": ["117 West St", "New York, NY 10007"]}, "phone": "+12126024000", "display_phone": "(212) 602-4000", "distance": 2943.019438207965}, {"id": "8HkB3JfIj7_g-MN5ujoRig", "alias": "grand-central-terminal-new-york", "name": "Grand Central Terminal", "image_url": "https://s3-media1.fl.yelpcdn.com/bphoto/C-hbiuAPVEciL6m071KysA/o.jpg", "is_closed": false, "url": "https://www.yelp.com/biz/grand-central-terminal-new-york?adjust_creative=dMFM0G7PB1QaTw51VlEhfg&utm_campaign=yelp_api_v3&utm_medium=api_v3_business_search&utm_source=dMFM0G7PB1QaTw51VlEhfg", "review_count": 1520, "categories": [{"alias": "landmarks", "title": "Landmarks & Historical Buildings"}, {"alias": "trainstations", "title": "Train Stations"}], "rating": 4.5, "coordinates": {"latitude": 40.752727697036576, "longitude": -73.97723946032279}, "transactions": [], "location": {"address1": "89 E 42nd St", "address2": null, "address3": "", "city": "New York", "zip_code": "10017", "country": "US", "state": "NY", "display_address": ["89 E 42nd St", "New York, NY 10017"]}, "phone": "+12123402583", "display_phone": "(212) 340-2583", "distance": 5089.806997562708}, {"id": "kViIWJFfAfWPpJOwAXBKGA", "alias": "national-september-11-memorial-museum-new-york", "name": "National September 11 Memorial Museum", "image_url": "https://s3-media4.fl.yelpcdn.com/bphoto/p2t5PSNsPNvdrZosA4K6iQ/o.jpg", "is_closed": false, "url": "https://www.yelp.com/biz/national-september-11-memorial-museum-new-york?adjust_creative=dMFM0G7PB1QaTw51VlEhfg&utm_campaign=yelp_api_v3&utm_medium=api_v3_business_search&utm_source=dMFM0G7PB1QaTw51VlEhfg", "review_count": 1567, "categories": [{"alias": "museums", "title": "Museums"}], "rating": 4.5, "coordinates": {"latitude": 40.71142179527282, "longitude": -74.01247659038673}, "transactions": [], "location": {"address1": "180 Greenwich St", "address2": "", "address3": "", "city": "New York", "zip_code": "10007", "country": "US", "state": "NY", "display_address": ["180 Greenwich St", "New York, NY 10007"]}, "phone": "+12122665211", "display_phone": "(212) 266-5211", "distance": 2849.1250713223967}], "total": 3300, "region": {"center": {"longitude": -73.97918701171875, "latitude": 40.706977710584276}}}